truss_utils/__init__.py
truss_utils/image.py
truss_utils-0.1.0.dist-info/METADATA
truss_utils-0.1.0.dist-info/WHEEL
truss_utils-0.1.0.dist-info/RECORD
