Metadata-Version: 2.1
Name: truss-utils
Version: 0.1.0
Summary: Utilities for use in Truss development
License: MIT
Author: Truss Maintainers
Author-email: team@trussml.com
Requires-Python: >=3.8,<3.12
Classifier: License :: OSI Approved :: MIT License
Classifier: Programming Language :: Python :: 3
Classifier: Programming Language :: Python :: 3.8
Classifier: Programming Language :: Python :: 3.9
Classifier: Programming Language :: Python :: 3.10
Classifier: Programming Language :: Python :: 3.11
Requires-Dist: Pillow (>=10.0.0,<11.0.0)
